cartoonizer.py
cartoonizer-0.0.4.dist-info/METADATA
cartoonizer-0.0.4.dist-info/WHEEL
cartoonizer-0.0.4.dist-info/license.txt
cartoonizer-0.0.4.dist-info/top_level.txt
cartoonizer-0.0.4.dist-info/RECORD
