Metadata-Version: 2.1
Name: cartoonizer
Version: 0.0.4
Summary: Convert your Image into a Cartoon form
Home-page: UNKNOWN
License: UNKNOWN
Platform: UNKNOWN
